WWOpenLabeling/__init__.py
WWOpenLabeling/annotator.py
WWOpenLabeling/dasiamrpn.py
WWOpenLabeling/main.py
WWOpenLabeling/main_auto.py
WWOpenLabeling/helper_utils/__init__.py
WWOpenLabeling/helper_utils/annotation_file_manager.py
WWOpenLabeling/helper_utils/vids_downloader.py
main/__init__.py
main/annotator.py
main/dasiamrpn.py
main/main.py
main/main_auto.py
WWOpenLabeling-1.0.5.dist-info/LICENSE
WWOpenLabeling-1.0.5.dist-info/METADATA
WWOpenLabeling-1.0.5.dist-info/WHEEL
WWOpenLabeling-1.0.5.dist-info/top_level.txt
WWOpenLabeling-1.0.5.dist-info/RECORD
